README.md
pyproject.toml
setup.py
src/math_adhit/__init__.py
src/math_adhit/aritmatika.py
src/math_adhit/bangun_ruang.py
src/math_package_adhit.egg-info/PKG-INFO
src/math_package_adhit.egg-info/SOURCES.txt
src/math_package_adhit.egg-info/dependency_links.txt
src/math_package_adhit.egg-info/top_level.txt