Metadata-Version: 2.1
Name: math-package-adhit
Version: 0.3.2
Summary: rumus matematika
Home-page: https://github.com/pypa/sampleproject
Author: adhitya Prasetio
Author-email: adhitya.prasetio01@gmail.com
License: UNKNOWN
Project-URL: Bug Tracker, https://github.com/pypa/sampleproject/issues
Platform: UNKNOWN
Classifier: Programming Language :: Python :: 3
Classifier: License :: OSI Approved :: MIT License
Classifier: Operating System :: OS Independent
Requires-Python: >=3.6
